setup.py
distributions_binomialgaussian/Binomialdistribution.py
distributions_binomialgaussian/Gaussiandistribution.py
distributions_binomialgaussian/Generaldistribution.py
distributions_binomialgaussian/__init__.py
distributions_binomialgaussian.egg-info/PKG-INFO
distributions_binomialgaussian.egg-info/SOURCES.txt
distributions_binomialgaussian.egg-info/dependency_links.txt
distributions_binomialgaussian.egg-info/not-zip-safe
distributions_binomialgaussian.egg-info/top_level.txt